[
  {
    "date": "2025-06-06",
    "timestamp": "2025-08-26T14:29:42.876699",
    "22k": 8995.0,
    "24k": 9445.0,
    "currency": "INR",
    "unit": "1 Gram",
    "status_code": 200
  },
  {
    "date": "2025-06-07",
    "timestamp": "2025-08-26T14:29:42.494268",
    "22k": 8995.0,
    "24k": 9445.0,
    "currency": "INR",
    "unit": "1 Gram",
    "status_code": 200
  },
  {
    "date": "2025-06-08",
    "timestamp": "2025-08-26T14:29:42.024256",
    "22k": 8995.0,
    "24k": 9445.0,
    "currency": "INR",
    "unit": "1 Gram",
    "status_code": 200
  },
  {
    "date": "2025-06-09",
    "timestamp": "2025-08-26T14:29:41.640274",
    "22k": 8995.0,
    "24k": 9445.0,
    "currency": "INR",
    "unit": "1 Gram",
    "status_code": 200
  },
  {
    "date": "2025-06-10",
    "timestamp": "2025-08-26T14:29:41.266093",
    "22k": 8995.0,
    "24k": 9445.0,
    "currency": "INR",
    "unit": "1 Gram",
    "status_code": 200
  },
  {
    "date": "2025-06-11",
    "timestamp": "2025-08-26T14:29:40.872361",
    "22k": 8995.0,
    "24k": 9445.0,
    "currency": "INR",
    "unit": "1 Gram",
    "status_code": 200
  },
  {
    "date": "2025-06-12",
    "timestamp": "2025-08-26T14:29:40.497663",
    "22k": 8995.0,
    "24k": 9445.0,
    "currency": "INR",
    "unit": "1 Gram",
    "status_code": 200
  },
  {
    "date": "2025-06-13",
    "timestamp": "2025-08-26T14:29:40.116788",
    "22k": 8995.0,
    "24k": 9445.0,
    "currency": "INR",
    "unit": "1 Gram",
    "status_code": 200
  },
  {
    "date": "2025-06-14",
    "timestamp": "2025-08-26T14:29:39.740090",
    "22k": 8995.0,
    "24k": 9445.0,
    "currency": "INR",
    "unit": "1 Gram",
    "status_code": 200
  },
  {
    "date": "2025-06-15",
    "timestamp": "2025-08-26T14:29:39.342322",
    "22k": 8995.0,
    "24k": 9445.0,
    "currency": "INR",
    "unit": "1 Gram",
    "status_code": 200
  },
  {
    "date": "2025-06-16",
    "timestamp": "2025-08-26T14:29:38.963617",
    "22k": 8995.0,
    "24k": 9445.0,
    "currency": "INR",
    "unit": "1 Gram",
    "status_code": 200
  },
  {
    "date": "2025-06-17",
    "timestamp": "2025-08-26T14:29:38.585711",
    "22k": 8995.0,
    "24k": 9445.0,
    "currency": "INR",
    "unit": "1 Gram",
    "status_code": 200
  },
  {
    "date": "2025-06-18",
    "timestamp": "2025-08-26T14:29:38.207558",
    "22k": 8995.0,
    "24k": 9445.0,
    "currency": "INR",
    "unit": "1 Gram",
    "status_code": 200
  },
  {
    "date": "2025-06-19",
    "timestamp": "2025-08-26T14:29:37.819452",
    "22k": 8995.0,
    "24k": 9445.0,
    "currency": "INR",
    "unit": "1 Gram",
    "status_code": 200
  },
  {
    "date": "2025-06-20",
    "timestamp": "2025-08-26T14:29:37.432071",
    "22k": 8995.0,
    "24k": 9445.0,
    "currency": "INR",
    "unit": "1 Gram",
    "status_code": 200
  },
  {
    "date": "2025-06-21",
    "timestamp": "2025-08-26T14:29:37.032439",
    "22k": 8995.0,
    "24k": 9445.0,
    "currency": "INR",
    "unit": "1 Gram",
    "status_code": 200
  },
  {
    "date": "2025-06-22",
    "timestamp": "2025-08-26T14:29:36.577739",
    "22k": 8995.0,
    "24k": 9445.0,
    "currency": "INR",
    "unit": "1 Gram",
    "status_code": 200
  },
  {
    "date": "2025-06-23",
    "timestamp": "2025-08-26T14:29:36.094791",
    "22k": 8995.0,
    "24k": 9445.0,
    "currency": "INR",
    "unit": "1 Gram",
    "status_code": 200
  },
  {
    "date": "2025-06-24",
    "timestamp": "2025-08-26T14:29:35.606286",
    "22k": 8995.0,
    "24k": 9445.0,
    "currency": "INR",
    "unit": "1 Gram",
    "status_code": 200
  },
  {
    "date": "2025-06-25",
    "timestamp": "2025-08-26T14:29:35.160532",
    "22k": 8995.0,
    "24k": 9445.0,
    "currency": "INR",
    "unit": "1 Gram",
    "status_code": 200
  },
  {
    "date": "2025-06-26",
    "timestamp": "2025-08-26T14:29:34.737991",
    "22k": 8995.0,
    "24k": 9445.0,
    "currency": "INR",
    "unit": "1 Gram",
    "status_code": 200
  },
  {
    "date": "2025-06-27",
    "timestamp": "2025-08-26T14:29:34.326312",
    "22k": 8995.0,
    "24k": 9445.0,
    "currency": "INR",
    "unit": "1 Gram",
    "status_code": 200
  },
  {
    "date": "2025-06-28",
    "timestamp": "2025-08-26T14:29:33.915928",
    "22k": 8995.0,
    "24k": 9445.0,
    "currency": "INR",
    "unit": "1 Gram",
    "status_code": 200
  },
  {
    "date": "2025-06-29",
    "timestamp": "2025-08-26T14:29:33.499614",
    "22k": 8995.0,
    "24k": 9445.0,
    "currency": "INR",
    "unit": "1 Gram",
    "status_code": 200
  },
  {
    "date": "2025-06-30",
    "timestamp": "2025-08-26T14:29:33.087816",
    "22k": 8995.0,
    "24k": 9445.0,
    "currency": "INR",
    "unit": "1 Gram",
    "status_code": 200
  },
  {
    "date": "2025-07-01",
    "timestamp": "2025-08-26T14:29:32.679266",
    "22k": 9240.0,
    "24k": 9702.0,
    "currency": "INR",
    "unit": "1 Gram",
    "status_code": 200
  },
  {
    "date": "2025-07-02",
    "timestamp": "2025-08-26T14:29:32.277671",
    "22k": 9240.0,
    "24k": 9702.0,
    "currency": "INR",
    "unit": "1 Gram",
    "status_code": 200
  },
  {
    "date": "2025-07-03",
    "timestamp": "2025-08-26T14:29:31.859253",
    "22k": 9240.0,
    "24k": 9702.0,
    "currency": "INR",
    "unit": "1 Gram",
    "status_code": 200
  },
  {
    "date": "2025-07-04",
    "timestamp": "2025-08-26T14:29:31.449627",
    "22k": 9240.0,
    "24k": 9702.0,
    "currency": "INR",
    "unit": "1 Gram",
    "status_code": 200
  },
  {
    "date": "2025-07-05",
    "timestamp": "2025-08-26T14:29:31.039654",
    "22k": 9240.0,
    "24k": 9702.0,
    "currency": "INR",
    "unit": "1 Gram",
    "status_code": 200
  },
  {
    "date": "2025-07-06",
    "timestamp": "2025-08-26T14:29:30.630577",
    "22k": 9240.0,
    "24k": 9702.0,
    "currency": "INR",
    "unit": "1 Gram",
    "status_code": 200
  },
  {
    "date": "2025-07-07",
    "timestamp": "2025-08-26T14:29:30.134980",
    "22k": 9240.0,
    "24k": 9702.0,
    "currency": "INR",
    "unit": "1 Gram",
    "status_code": 200
  },
  {
    "date": "2025-07-08",
    "timestamp": "2025-08-26T14:29:29.725058",
    "22k": 9240.0,
    "24k": 9702.0,
    "currency": "INR",
    "unit": "1 Gram",
    "status_code": 200
  },
  {
    "date": "2025-07-09",
    "timestamp": "2025-08-26T14:29:29.346659",
    "22k": 9240.0,
    "24k": 9702.0,
    "currency": "INR",
    "unit": "1 Gram",
    "status_code": 200
  },
  {
    "date": "2025-07-10",
    "timestamp": "2025-08-26T14:29:28.936863",
    "22k": 9240.0,
    "24k": 9702.0,
    "currency": "INR",
    "unit": "1 Gram",
    "status_code": 200
  },
  {
    "date": "2025-07-11",
    "timestamp": "2025-08-26T14:29:28.444992",
    "22k": 9240.0,
    "24k": 9702.0,
    "currency": "INR",
    "unit": "1 Gram",
    "status_code": 200
  },
  {
    "date": "2025-07-12",
    "timestamp": "2025-08-26T14:29:28.069844",
    "22k": 9240.0,
    "24k": 9702.0,
    "currency": "INR",
    "unit": "1 Gram",
    "status_code": 200
  },
  {
    "date": "2025-07-13",
    "timestamp": "2025-08-26T14:29:27.669772",
    "22k": 9240.0,
    "24k": 9702.0,
    "currency": "INR",
    "unit": "1 Gram",
    "status_code": 200
  },
  {
    "date": "2025-07-14",
    "timestamp": "2025-08-26T14:29:27.270981",
    "22k": 9240.0,
    "24k": 9702.0,
    "currency": "INR",
    "unit": "1 Gram",
    "status_code": 200
  },
  {
    "date": "2025-07-15",
    "timestamp": "2025-08-26T14:29:26.899530",
    "22k": 9240.0,
    "24k": 9702.0,
    "currency": "INR",
    "unit": "1 Gram",
    "status_code": 200
  },
  {
    "date": "2025-07-16",
    "timestamp": "2025-08-26T14:29:26.513501",
    "22k": 9240.0,
    "24k": 9702.0,
    "currency": "INR",
    "unit": "1 Gram",
    "status_code": 200
  },
  {
    "date": "2025-07-17",
    "timestamp": "2025-08-26T14:29:26.133643",
    "22k": 9240.0,
    "24k": 9702.0,
    "currency": "INR",
    "unit": "1 Gram",
    "status_code": 200
  },
  {
    "date": "2025-07-18",
    "timestamp": "2025-08-26T14:29:25.742132",
    "22k": 9240.0,
    "24k": 9702.0,
    "currency": "INR",
    "unit": "1 Gram",
    "status_code": 200
  },
  {
    "date": "2025-07-19",
    "timestamp": "2025-08-26T14:29:25.347795",
    "22k": 9240.0,
    "24k": 9702.0,
    "currency": "INR",
    "unit": "1 Gram",
    "status_code": 200
  },
  {
    "date": "2025-07-20",
    "timestamp": "2025-08-26T14:29:24.964089",
    "22k": 9240.0,
    "24k": 9702.0,
    "currency": "INR",
    "unit": "1 Gram",
    "status_code": 200
  },
  {
    "date": "2025-07-21",
    "timestamp": "2025-08-26T14:29:24.574127",
    "22k": 9240.0,
    "24k": 9702.0,
    "currency": "INR",
    "unit": "1 Gram",
    "status_code": 200
  },
  {
    "date": "2025-07-22",
    "timestamp": "2025-08-26T14:29:24.188504",
    "22k": 9240.0,
    "24k": 9702.0,
    "currency": "INR",
    "unit": "1 Gram",
    "status_code": 200
  },
  {
    "date": "2025-07-23",
    "timestamp": "2025-08-26T14:29:23.807570",
    "22k": 9240.0,
    "24k": 9702.0,
    "currency": "INR",
    "unit": "1 Gram",
    "status_code": 200
  },
  {
    "date": "2025-07-24",
    "timestamp": "2025-08-26T14:29:23.307581",
    "22k": 9240.0,
    "24k": 9702.0,
    "currency": "INR",
    "unit": "1 Gram",
    "status_code": 200
  },
  {
    "date": "2025-07-25",
    "timestamp": "2025-08-26T14:29:22.857536",
    "22k": 9240.0,
    "24k": 9702.0,
    "currency": "INR",
    "unit": "1 Gram",
    "status_code": 200
  },
  {
    "date": "2025-07-26",
    "timestamp": "2025-08-26T14:29:22.471819",
    "22k": 9240.0,
    "24k": 9702.0,
    "currency": "INR",
    "unit": "1 Gram",
    "status_code": 200
  },
  {
    "date": "2025-07-27",
    "timestamp": "2025-08-26T14:29:22.042382",
    "22k": 9240.0,
    "24k": 9702.0,
    "currency": "INR",
    "unit": "1 Gram",
    "status_code": 200
  },
  {
    "date": "2025-07-28",
    "timestamp": "2025-08-26T14:29:21.647383",
    "22k": 9240.0,
    "24k": 9702.0,
    "currency": "INR",
    "unit": "1 Gram",
    "status_code": 200
  },
  {
    "date": "2025-07-29",
    "timestamp": "2025-08-26T14:29:21.240810",
    "22k": 9240.0,
    "24k": 9702.0,
    "currency": "INR",
    "unit": "1 Gram",
    "status_code": 200
  },
  {
    "date": "2025-07-30",
    "timestamp": "2025-08-26T14:29:20.808176",
    "22k": 9240.0,
    "24k": 9702.0,
    "currency": "INR",
    "unit": "1 Gram",
    "status_code": 200
  },
  {
    "date": "2025-07-31",
    "timestamp": "2025-08-26T14:29:20.299788",
    "22k": 9240.0,
    "24k": 9702.0,
    "currency": "INR",
    "unit": "1 Gram",
    "status_code": 200
  },
  {
    "date": "2025-08-01",
    "timestamp": "2025-08-26T14:29:19.911954",
    "22k": 9420.0,
    "24k": 9891.0,
    "currency": "INR",
    "unit": "1 Gram",
    "status_code": 200
  },
  {
    "date": "2025-08-02",
    "timestamp": "2025-08-26T14:29:19.532675",
    "22k": 9420.0,
    "24k": 9891.0,
    "currency": "INR",
    "unit": "1 Gram",
    "status_code": 200
  },
  {
    "date": "2025-08-03",
    "timestamp": "2025-08-26T14:29:19.118902",
    "22k": 9420.0,
    "24k": 9891.0,
    "currency": "INR",
    "unit": "1 Gram",
    "status_code": 200
  },
  {
    "date": "2025-08-04",
    "timestamp": "2025-08-26T14:29:18.626736",
    "22k": 9420.0,
    "24k": 9891.0,
    "currency": "INR",
    "unit": "1 Gram",
    "status_code": 200
  },
  {
    "date": "2025-08-05",
    "timestamp": "2025-08-26T14:29:18.240488",
    "22k": 9420.0,
    "24k": 9891.0,
    "currency": "INR",
    "unit": "1 Gram",
    "status_code": 200
  },
  {
    "date": "2025-08-06",
    "timestamp": "2025-08-26T14:29:17.778788",
    "22k": 9420.0,
    "24k": 9891.0,
    "currency": "INR",
    "unit": "1 Gram",
    "status_code": 200
  },
  {
    "date": "2025-08-07",
    "timestamp": "2025-08-26T14:29:17.285155",
    "22k": 9420.0,
    "24k": 9891.0,
    "currency": "INR",
    "unit": "1 Gram",
    "status_code": 200
  },
  {
    "date": "2025-08-08",
    "timestamp": "2025-08-26T14:29:16.831909",
    "22k": 9420.0,
    "24k": 9891.0,
    "currency": "INR",
    "unit": "1 Gram",
    "status_code": 200
  },
  {
    "date": "2025-08-09",
    "timestamp": "2025-08-26T14:29:16.394683",
    "22k": 9420.0,
    "24k": 9891.0,
    "currency": "INR",
    "unit": "1 Gram",
    "status_code": 200
  },
  {
    "date": "2025-08-10",
    "timestamp": "2025-08-26T14:29:15.979966",
    "22k": 9420.0,
    "24k": 9891.0,
    "currency": "INR",
    "unit": "1 Gram",
    "status_code": 200
  },
  {
    "date": "2025-08-11",
    "timestamp": "2025-08-26T14:29:15.474392",
    "22k": 9420.0,
    "24k": 9891.0,
    "currency": "INR",
    "unit": "1 Gram",
    "status_code": 200
  },
  {
    "date": "2025-08-12",
    "timestamp": "2025-08-26T14:29:15.053863",
    "22k": 9420.0,
    "24k": 9891.0,
    "currency": "INR",
    "unit": "1 Gram",
    "status_code": 200
  },
  {
    "date": "2025-08-13",
    "timestamp": "2025-08-26T14:29:14.653875",
    "22k": 9420.0,
    "24k": 9891.0,
    "currency": "INR",
    "unit": "1 Gram",
    "status_code": 200
  },
  {
    "date": "2025-08-14",
    "timestamp": "2025-08-26T14:29:14.153357",
    "22k": 9420.0,
    "24k": 9891.0,
    "currency": "INR",
    "unit": "1 Gram",
    "status_code": 200
  },
  {
    "date": "2025-08-15",
    "timestamp": "2025-08-26T14:29:13.734783",
    "22k": 9420.0,
    "24k": 9891.0,
    "currency": "INR",
    "unit": "1 Gram",
    "status_code": 200
  },
  {
    "date": "2025-08-16",
    "timestamp": "2025-08-26T14:29:13.338791",
    "22k": 9420.0,
    "24k": 9891.0,
    "currency": "INR",
    "unit": "1 Gram",
    "status_code": 200
  },
  {
    "date": "2025-08-17",
    "timestamp": "2025-08-26T14:29:12.936394",
    "22k": 9420.0,
    "24k": 9891.0,
    "currency": "INR",
    "unit": "1 Gram",
    "status_code": 200
  },
  {
    "date": "2025-08-18",
    "timestamp": "2025-08-26T14:29:12.534202",
    "22k": 9420.0,
    "24k": 9891.0,
    "currency": "INR",
    "unit": "1 Gram",
    "status_code": 200
  },
  {
    "date": "2025-08-19",
    "timestamp": "2025-08-26T14:29:12.148449",
    "22k": 9420.0,
    "24k": 9891.0,
    "currency": "INR",
    "unit": "1 Gram",
    "status_code": 200
  },
  {
    "date": "2025-08-20",
    "timestamp": "2025-08-26T14:29:11.747535",
    "22k": 9420.0,
    "24k": 9891.0,
    "currency": "INR",
    "unit": "1 Gram",
    "status_code": 200
  },
  {
    "date": "2025-08-21",
    "timestamp": "2025-08-26T14:29:11.360022",
    "22k": 9420.0,
    "24k": 9891.0,
    "currency": "INR",
    "unit": "1 Gram",
    "status_code": 200
  },
  {
    "date": "2025-08-22",
    "timestamp": "2025-08-26T14:29:10.966943",
    "22k": 9420.0,
    "24k": 9891.0,
    "currency": "INR",
    "unit": "1 Gram",
    "status_code": 200
  },
  {
    "date": "2025-08-23",
    "timestamp": "2025-08-26T14:29:10.588026",
    "22k": 9420.0,
    "24k": 9891.0,
    "currency": "INR",
    "unit": "1 Gram",
    "status_code": 200
  },
  {
    "date": "2025-08-24",
    "timestamp": "2025-08-26T14:29:10.190854",
    "22k": 9420.0,
    "24k": 9891.0,
    "currency": "INR",
    "unit": "1 Gram",
    "status_code": 200
  },
  {
    "date": "2025-08-25",
    "timestamp": "2025-08-26T14:29:09.708140",
    "22k": 9420.0,
    "24k": 9891.0,
    "currency": "INR",
    "unit": "1 Gram",
    "status_code": 200
  },
  {
    "date": "2025-08-26",
    "timestamp": "2025-08-26T14:29:09.281102",
    "22k": 9420.0,
    "24k": 9891.0,
    "currency": "INR",
    "unit": "1 Gram",
    "status_code": 200
  },
  {
    "date": "2025-08-29",
    "timestamp": "2025-08-29T16:07:09.295192",
    "22k": 9535.0,
    "24k": 10012.0,
    "currency": "INR",
    "unit": "1 Gram",
    "status_code": 200
  },
  {
    "date": "2025-09-01",
    "timestamp": "2025-09-01T17:07:29.216400",
    "22k": 9770.0,
    "24k": 10259.0,
    "currency": "INR",
    "unit": "1 Gram",
    "status_code": 200
  },
  {
    "date": "2025-09-02",
    "timestamp": "2025-09-02T17:35:39.838133",
    "22k": 9790.0,
    "24k": 10280.0,
    "currency": "INR",
    "unit": "1 Gram",
    "status_code": 200
  },
  {
    "date": "2025-09-03",
    "timestamp": "2025-09-03T17:39:41.546148",
    "22k": 9870.0,
    "24k": 10364.0,
    "currency": "INR",
    "unit": "1 Gram",
    "status_code": 200
  },
  {
    "date": "2025-09-09",
    "timestamp": "2025-09-09T11:24:53.833768",
    "22k": 9999.99,
    "24k": 10500.0,
    "currency": "INR",
    "unit": "1 Gram",
    "status_code": 200
  },
  {
    "date": "2025-09-10",
    "timestamp": "2025-09-10T01:54:48.991948",
    "22k": 9999.99,
    "24k": 10500.0,
    "currency": "INR",
    "unit": "1 Gram",
    "status_code": 200
  },
  {
    "date": "2025-09-11",
    "timestamp": "2025-09-11T01:58:05.805730",
    "22k": 9999.99,
    "24k": 10500.0,
    "currency": "INR",
    "unit": "1 Gram",
    "status_code": 200
  },
  {
    "date": "2025-09-12",
    "timestamp": "2025-09-12T01:53:40.141894",
    "22k": 10130,
    "24k": 11059,
    "currency": "INR",
    "unit": "1 Gram",
    "status_code": 200
  }
]