[
  {
    "date": "2025-06-15",
    "price_22k": 9070.27,
    "price_24k": 9735.31
  },
  {
    "date": "2025-06-16",
    "price_22k": 9025.05,
    "price_24k": 9681.62
  },
  {
    "date": "2025-06-17",
    "price_22k": 9315.27,
    "price_24k": 9526.4
  },
  {
    "date": "2025-06-18",
    "price_22k": 9257.67,
    "price_24k": 9669.08
  },
  {
    "date": "2025-06-19",
    "price_22k": 9038.41,
    "price_24k": 9666.59
  },
  {
    "date": "2025-06-20",
    "price_22k": 9090.27,
    "price_24k": 9479.36
  },
  {
    "date": "2025-06-21",
    "price_22k": 9295.31,
    "price_24k": 9612.09
  },
  {
    "date": "2025-06-22",
    "price_22k": 9154.34,
    "price_24k": 9669.74
  },
  {
    "date": "2025-06-23",
    "price_22k": 9303.26,
    "price_24k": 9492.54
  },
  {
    "date": "2025-06-24",
    "price_22k": 9155.0,
    "price_24k": 9613.0
  }
]