[
  {
    "date": "2025-06-15",
    "price_22k": 9332.12,
    "price_24k": 9855.42
  },
  {
    "date": "2025-06-16",
    "price_22k": 9139.7,
    "price_24k": 9548.65
  },
  {
    "date": "2025-06-17",
    "price_22k": 9089.39,
    "price_24k": 9579.66
  },
  {
    "date": "2025-06-18",
    "price_22k": 9066.0,
    "price_24k": 9532.64
  },
  {
    "date": "2025-06-19",
    "price_22k": 9249.28,
    "price_24k": 9728.16
  },
  {
    "date": "2025-06-20",
    "price_22k": 9122.63,
    "price_24k": 9520.83
  },
  {
    "date": "2025-06-21",
    "price_22k": 9173.09,
    "price_24k": 9631.42
  },
  {
    "date": "2025-06-22",
    "price_22k": 9168.33,
    "price_24k": 9748.37
  },
  {
    "date": "2025-06-23",
    "price_22k": 9153.81,
    "price_24k": 9850.76
  },
  {
    "date": "2025-06-24",
    "price_22k": 9235.0,
    "price_24k": 9697.0
  }
]